{
  "properties": [
    {
      "name": "keywords",
      "type": "java.lang.String",
      "description": "Description for keywords."
    },
    {
      "name": "file.corpus.prefix",
      "type": "java.lang.String",
      "description": "Description for file.corpus.prefix."
    },
    {
      "name": "dir.crawler.sleep.time",
      "type": "java.lang.String",
      "description": "Description for dir.crawler.sleep.time."
    },
    {
      "name": "file.scanning.size.limit",
      "type": "java.lang.String",
      "description": "Description for file.scanning.size.limit."
    },
    {
      "name": "hop.count",
      "type": "java.lang.String",
      "description": "Description for hop.count."
    },
    {
      "name": "url.refresh.time",
      "type": "java.lang.String",
      "description": "Description for url.refresh.time."
    }
  ] }